metatrt/__init__.py
metatrt/app/__init__.py
metatrt/app/instance_segment_trt.py
metatrt/app/object_classification_trt.py
metatrt/app/object_detection_trt.py
metatrt/app/onnx_to_trt.py
metatrt/app/saliency_segment_trt.py
metatrt/model_zoo/__init__.py
metatrt/model_zoo/classification_trt_predictor.py
metatrt/model_zoo/detection_trt_predictor.py
metatrt/model_zoo/instance_trt_predictor.py
metatrt/model_zoo/segment_trt_predictor.py
metatrt/model_zoo/trt_export.py
metatrt/utils/__init__.py
metatrt/utils/general.py
metatrt/utils/image_batch.py
metatrt/utils/utils.py
meta_trt-3.9.18.dist-info/METADATA
meta_trt-3.9.18.dist-info/WHEEL
meta_trt-3.9.18.dist-info/top_level.txt
meta_trt-3.9.18.dist-info/zip-safe
meta_trt-3.9.18.dist-info/RECORD
