Metadata-Version: 2.1
Name: meta-trt
Version: 3.9.18
Summary: Meta Trt Toolkit
Home-page: https://github.com/CachCheng/cvtrt
Author: CachCheng
Author-email: tkggpdc2007@163.com
License: Apache-2.0
Requires-Dist: opencv-python
Requires-Dist: setuptools
Requires-Dist: tensorrt
Requires-Dist: pycuda
Requires-Dist: numpy
Requires-Dist: pillow
